{
   "playersv2": [
      {
         "group": null,
         "name": "m@rmot",
         "avatar": "https://steamcdn-a.akamaihd.net/steamcommunity/public/images/avatars/b7/b7ec8f5df07bd4460ab3da9c0ec86df9fba2f713_full.jpg",
         "country": "ru",
         "faceit_level": 3,
         "cybershoke_level": 5,
         "steamid64": "76561198970572610",
         "server_ip": "37.230.228.60",
         "server_port": 27020,
         "kills": 22,
         "headshots": 11,
         "deaths": 15,
         "time": 900,
         "FACEIT_elo": 1073
      },
      {
         "group": null,
         "name": "kill lil",
         "avatar": "https://steamcdn-a.akamaihd.net/steamcommunity/public/images/avatars/1a/1a2bb09a28d4a30c1caed3af7b54dbaed6be4534_full.jpg",
         "country": "ru",
         "faceit_level": 4,
         "cybershoke_level": 14,
         "steamid64": "76561198832484318",
         "server_ip": "37.230.228.60",
         "server_port": 27020,
         "kills": 18,
         "headshots": 10,
         "deaths": 16,
         "time": 900,
         "FACEIT_elo": 1194
      },
      {
         "group": null,
         "name": "\u0420\u043e\u043c\u0430\u0437\u0435\u0441\u0441\u0441666",
         "avatar": "https://steamcdn-a.akamaihd.net/steamcommunity/public/images/avatars/e7/e73f6fadbf76670c088cd8f8d0a67b6c2eb7561f_full.jpg",
         "country": "ru",
         "faceit_level": 1,
         "cybershoke_level": 2,
         "steamid64": "76561198069839811",
         "server_ip": "37.230.228.60",
         "server_port": 27020,
         "kills": 6,
         "headshots": 4,
         "deaths": 1,
         "time": 214,
         "FACEIT_elo": 478
      },
      {
         "group": null,
         "name": "F4N1(3)",
         "avatar": "https://steamcdn-a.akamaihd.net/steamcommunity/public/images/avatars/ce/ce4463f8d9d73e6da2d4886179941667067ee89d_full.jpg",
         "country": "ru",
         "faceit_level": 1,
         "cybershoke_level": 3,
         "steamid64": "76561198196308290",
         "server_ip": "37.230.228.60",
         "server_port": 27020,
         "kills": 4,
         "headshots": 2,
         "deaths": 16,
         "time": 647,
         "FACEIT_elo": 778
      },
      {
         "group": null,
         "name": "kison",
         "avatar": "https://steamcdn-a.akamaihd.net/steamcommunity/public/images/avatars/44/446c72d788fe7e14a8d7a0306257da865405481b_full.jpg",
         "country": "ua",
         "faceit_level": 2,
         "cybershoke_level": 6,
         "steamid64": "76561199161326546",
         "server_ip": "37.230.228.60",
         "server_port": 27020,
         "kills": 2,
         "headshots": 2,
         "deaths": 3,
         "time": 169,
         "FACEIT_elo": 936
      },
      {
         "group": null,
         "name": "\u2745Bid\u0365\u01e4u\u0363y\u036b\u01e4u\u03b1\u2745",
         "avatar": "https://steamcdn-a.akamaihd.net/steamcommunity/public/images/avatars/74/74cf392846513eb35f4912ec1526dd5690aba00d_full.jpg",
         "country": "kz",
         "faceit_level": 1,
         "cybershoke_level": 4,
         "steamid64": "76561199001986266",
         "server_ip": "37.230.228.60",
         "server_port": 27020,
         "kills": 1,
         "headshots": 0,
         "deaths": 0,
         "time": 66,
         "FACEIT_elo": 495
      }
   ],
   "serversv2": {
      "0": {
         "ip": "37.230.228.60",
         "port": 27020,
         "Players": 6,
         "round_win_ct": 13,
         "round_win_t": 16,
         "match_start_time": 1646234844,
         "match_max_time": 3600,
         "match_max_round": 30,
         "map": "de_inferno",
         "max_players": 7,
         "players": 6,
         "faceit_avg": 2,
         "mode_alt": "RETAKE"
      }
   }
}