{
   "playersv2": [
      {
         "group": null,
         "name": "MeRzAv4ik",
         "avatar": "https://steamcdn-a.akamaihd.net/steamcommunity/public/images/avatars/fe/fe7e679ddf1869b5dab9ebddc0b74bbcf716a473_full.jpg",
         "country": "ru",
         "faceit_level": 1,
         "cybershoke_level": 6,
         "steamid64": "76561198033026327",
         "server_ip": "46.174.55.15",
         "server_port": 27018,
         "kills": 0,
         "headshots": 0,
         "deaths": 0,
         "time": 64,
         "FACEIT_elo": 538
      },
      {
         "group": null,
         "name": "SpongeBob",
         "avatar": "https://steamcdn-a.akamaihd.net/steamcommunity/public/images/avatars/0f/0ff4902917fe6efc6500fb501080f3453e0ad5af_full.jpg",
         "country": "ru",
         "faceit_level": 3,
         "cybershoke_level": 5,
         "steamid64": "76561198145874949",
         "server_ip": "46.174.55.15",
         "server_port": 27018,
         "kills": 0,
         "headshots": 0,
         "deaths": 0,
         "time": 17,
         "FACEIT_elo": 954
      },
      {
         "group": null,
         "name": "newmercedes",
         "avatar": "https://steamcdn-a.akamaihd.net/steamcommunity/public/images/avatars/fe/fe731dd23aaaf9af432d55ce3ee7c75e9d1fe39a_full.jpg",
         "country": "by",
         "faceit_level": 4,
         "cybershoke_level": 6,
         "steamid64": "76561198977282962",
         "server_ip": "46.174.55.15",
         "server_port": 27018,
         "kills": 0,
         "headshots": 0,
         "deaths": 0,
         "time": 23,
         "FACEIT_elo": 1124
      }
   ],
   "serversv2": {
      "0": {
         "ip": "46.174.55.15",
         "port": 27018,
         "Players": 3,
         "round_win_ct": 0,
         "round_win_t": 3,
         "match_start_time": 1646240009,
         "match_max_time": 3600,
         "match_max_round": 30,
         "map": "de_ancient",
         "max_players": 7,
         "players": 3,
         "faceit_avg": 3,
         "mode_alt": "RETAKE"
      }
   }
}